deriva_ml/.DS_Store
deriva_ml/__init__.py
deriva_ml/bump_version.py
deriva_ml/demo_catalog.py
deriva_ml/feature.py
deriva_ml/install_kernel.py
deriva_ml/interfaces.py
deriva_ml/run_model.py
deriva_ml/run_notebook.py
deriva_ml/asset/__init__.py
deriva_ml/asset/asset.py
deriva_ml/asset/aux_classes.py
deriva_ml/catalog/__init__.py
deriva_ml/catalog/clone.py
deriva_ml/catalog/localize.py
deriva_ml/core/__init__.py
deriva_ml/core/base.py
deriva_ml/core/config.py
deriva_ml/core/constants.py
deriva_ml/core/definitions.py
deriva_ml/core/enums.py
deriva_ml/core/ermrest.py
deriva_ml/core/exceptions.py
deriva_ml/core/filespec.py
deriva_ml/core/logging_config.py
deriva_ml/core/validation.py
deriva_ml/core/mixins/__init__.py
deriva_ml/core/mixins/annotation.py
deriva_ml/core/mixins/asset.py
deriva_ml/core/mixins/dataset.py
deriva_ml/core/mixins/execution.py
deriva_ml/core/mixins/feature.py
deriva_ml/core/mixins/file.py
deriva_ml/core/mixins/path_builder.py
deriva_ml/core/mixins/rid_resolution.py
deriva_ml/core/mixins/vocabulary.py
deriva_ml/core/mixins/workflow.py
deriva_ml/dataset/__init__.py
deriva_ml/dataset/aux_classes.py
deriva_ml/dataset/catalog_graph.py
deriva_ml/dataset/dataset.py
deriva_ml/dataset/dataset_bag.py
deriva_ml/dataset/history.py
deriva_ml/dataset/upload.py
deriva_ml/execution/__init__.py
deriva_ml/execution/base_config.py
deriva_ml/execution/environment.py
deriva_ml/execution/execution.py
deriva_ml/execution/execution_configuration.py
deriva_ml/execution/execution_record.py
deriva_ml/execution/find_caller.py
deriva_ml/execution/model_protocol.py
deriva_ml/execution/multirun_config.py
deriva_ml/execution/runner.py
deriva_ml/execution/workflow.py
deriva_ml/experiment/__init__.py
deriva_ml/experiment/experiment.py
deriva_ml/model/__init__.py
deriva_ml/model/annotations.py
deriva_ml/model/catalog.py
deriva_ml/model/database.py
deriva_ml/model/deriva_ml_database.py
deriva_ml/model/handles.py
deriva_ml/schema/__init__.py
deriva_ml/schema/annotations.py
deriva_ml-1.17.15.dist-info/licenses/LICENSE
deriva_ml-1.17.15.dist-info/METADATA
deriva_ml-1.17.15.dist-info/WHEEL
deriva_ml-1.17.15.dist-info/entry_points.txt
deriva_ml-1.17.15.dist-info/top_level.txt
deriva_ml-1.17.15.dist-info/RECORD
