Metadata-Version: 2.4
Name: deriva-ml
Version: 1.17.15
Summary: Utilities to simplify use of Dervia and Pandas to create reproducable ML pipelines
Author-email: ISRD <isrd-dev@isi.edu>
Requires-Python: >=3.12
License-File: LICENSE
Requires-Dist: bump-my-version
Requires-Dist: bdbag
Requires-Dist: deriva~=1.7.10
Requires-Dist: deepdiff
Requires-Dist: nbconvert
Requires-Dist: pandas
Requires-Dist: pydantic>=2.11
Requires-Dist: papermill
Requires-Dist: pandas-stubs
Requires-Dist: pyyaml
Requires-Dist: regex
Requires-Dist: semver>3.0.0
Requires-Dist: setuptools>=80
Requires-Dist: setuptools-scm>=8.0
Requires-Dist: nbstripout
Requires-Dist: hydra_zen
Requires-Dist: SQLAlchemy
Dynamic: license-file
